atmql/__init__.py
atmql/auth.py
atmql/cli.py
atmql/models.py
atmql/query_engine.py
atmql/visualization.py
atmql-0.1.0.dist-info/METADATA
atmql-0.1.0.dist-info/WHEEL
atmql-0.1.0.dist-info/entry_points.txt
atmql-0.1.0.dist-info/top_level.txt
atmql-0.1.0.dist-info/RECORD
