Metadata-Version: 2.4
Name: atmql
Version: 0.1.0
Summary: Advanced Topic Modeling Query Language with rich terminal visualization
Home-page: https://github.com/yourusername/atmql
Author: Louati Mahdi
Author-email: louatimahdi390@gmail.com
Classifier: Programming Language :: Python :: 3
Classifier: License :: OSI Approved :: MIT License
Classifier: Operating System :: OS Independent
Requires-Python: >=3.7
Requires-Dist: numpy>=1.21.0
Requires-Dist: pandas>=1.3.0
Requires-Dist: scikit-learn>=1.0.0
Requires-Dist: gensim>=4.0.0
Requires-Dist: tabulate>=0.8.9
Requires-Dist: matplotlib>=3.4.0
Requires-Dist: seaborn>=0.11.0
Requires-Dist: pyfiglet>=0.8.post1
Requires-Dist: termcolor>=1.1.0
Requires-Dist: tqdm>=4.62.0
Requires-Dist: python-dotenv>=0.19.0
Requires-Dist: smtplib
Requires-Dist: email
Dynamic: author
Dynamic: author-email
Dynamic: classifier
Dynamic: description
Dynamic: description-content-type
Dynamic: home-page
Dynamic: requires-dist
Dynamic: requires-python
Dynamic: summary
